polarion_rest_api_client
