Metadata-Version: 2.4
Name: polarion-rest-api-client
Version: 1.4.6
Summary: An API Client for the Polarion REST API
Author: DB InfraGO AG
License-Expression: Apache-2.0
Project-URL: Homepage, https://github.com/dbinfrago/polarion-rest-api-client
Project-URL: Documentation, https://dbinfrago.github.io/polarion-rest-api-client
Platform: any
Classifier: Development Status :: 5 - Production/Stable
Classifier: Natural Language :: English
Classifier: Operating System :: OS Independent
Classifier: Programming Language :: Python :: 3 :: Only
Classifier: Programming Language :: Python :: 3.10
Classifier: Programming Language :: Python :: 3.11
Classifier: Programming Language :: Python :: 3.12
Classifier: Programming Language :: Python :: 3.13
Requires-Python: <3.14,>=3.10
License-File: LICENSES/Apache-2.0.txt
License-File: LICENSES/CC0-1.0.txt
Requires-Dist: httpx<0.29.0,>=0.20.0
Requires-Dist: attrs>=21.3.0
Requires-Dist: python-dateutil>=2.8.0
Requires-Dist: truststore>=0.10.1
Dynamic: license-file
